MANIFEST.in
README.md
setup.cfg
setup.py
prichardassets/__init__.py
prichardassets/hello.txt
prichardassets.egg-info/PKG-INFO
prichardassets.egg-info/SOURCES.txt
prichardassets.egg-info/dependency_links.txt
prichardassets.egg-info/top_level.txt