Metadata-Version: 1.0
Name: prichardassets
Version: 1.3
Summary: A module with a static file in it
Home-page: UNKNOWN
Author: prichard
Author-email: philippe.richard93@gmail.com
License: UNKNOWN
Platform: UNKNOWN
